LICENSE
README.md
setup.py
mimicbot_cli/__init__.py
mimicbot_cli/__main__.py
mimicbot_cli/cli.py
mimicbot_cli/config.py
mimicbot_cli/data_preprocessing.py
mimicbot_cli/setup.py
mimicbot_cli/train.py
mimicbot_cli/types.py
mimicbot_cli/utils.py
mimicbot_cli.egg-info/PKG-INFO
mimicbot_cli.egg-info/SOURCES.txt
mimicbot_cli.egg-info/dependency_links.txt
mimicbot_cli.egg-info/requires.txt
mimicbot_cli.egg-info/top_level.txt
mimicbot_cli/bot/__init__.py
mimicbot_cli/bot/mimic.py
mimicbot_cli/bot/mine.py
mimicbot_cli/huggingface/README.md
mimicbot_cli/huggingface/__init__.py
mimicbot_cli/mimicbot_chat/__init__.py
mimicbot_cli/mimicbot_chat/utils.py
tests/__init__.py
tests/test_init.py
tests/test_preprocess.py
tests/test_train.py