Metadata-Version: 2.1
Name: mimicbot-cli
Version: 1.0.1
Summary: Tools and a pipeline for creating of an AI chat bot modeled to imitate a user
Home-page: https://github.com/CakeCrusher/mimicbot
Author: Sebastian Sosa
Author-email: 1sebastian1sosa1@gmail.com
License: MIT License
Platform: UNKNOWN
Classifier: Development Status :: 3 - Alpha
Classifier: Intended Audience :: Science/Research
Classifier: License :: OSI Approved :: MIT License
Classifier: Programming Language :: Python :: 3.10
License-File: LICENSE
